neon_stt_plugin_coqui/__init__.py
neon_stt_plugin_coqui/coqui_models.yml
neon_stt_plugin_coqui-0.0.2a9.dist-info/LICENSE.md
neon_stt_plugin_coqui-0.0.2a9.dist-info/METADATA
neon_stt_plugin_coqui-0.0.2a9.dist-info/WHEEL
neon_stt_plugin_coqui-0.0.2a9.dist-info/entry_points.txt
neon_stt_plugin_coqui-0.0.2a9.dist-info/top_level.txt
neon_stt_plugin_coqui-0.0.2a9.dist-info/zip-safe
neon_stt_plugin_coqui-0.0.2a9.dist-info/RECORD
