Metadata-Version: 2.1
Name: neon-stt-plugin-coqui
Version: 0.0.2a9
Summary: A Polyglot stt plugin for Neon
Home-page: https://github.com/NeonGeckoCom/neon-stt-plugin-polyglot
Author: Neongecko
Author-email: mariia@neon.ai
License: BSD-3.0
Keywords: mycroft plugin stt
Platform: UNKNOWN
Classifier: Intended Audience :: Developers
Classifier: Topic :: Text Processing :: Linguistic
Classifier: Programming Language :: Python :: 3.6
Requires-Dist: dataclasses
Requires-Dist: ovos-lingua-franca (>=0.4.4a2)
Requires-Dist: tensorflow (==2.4.0)
Requires-Dist: ovos-plugin-manager (~=0.0.2)
Requires-Dist: ovos-utils (~=0.0.12)
Requires-Dist: neon-utils[audio] (<2.0,>=0.16)
Requires-Dist: wave
Requires-Dist: deepspeech
Requires-Dist: pyyaml (~=5.1)
